LICENSE
README.md
setup.py
steam/__init__.py
steam/api.py
steam/apps.py
steam/items.py
steam/loc.py
steam/remote_storage.py
steam/sim.py
steam/user.py
steam/vdf.py
steamodd.egg-info/PKG-INFO
steamodd.egg-info/SOURCES.txt
steamodd.egg-info/dependency_links.txt
steamodd.egg-info/top_level.txt