Metadata-Version: 2.1
Name: steamodd
Version: 4.23
Summary: High level Steam API implementation with low level reusable core
Home-page: https://github.com/Lagg/steamodd
Author: Anthony Garcia
Author-email: anthony@lagg.me
License: ISC
Platform: UNKNOWN
Classifier: License :: OSI Approved :: ISC License (ISCL)
Classifier: Intended Audience :: Developers
Classifier: Operating System :: OS Independent
Classifier: Programming Language :: Python
License-File: LICENSE
